{
    "actionOnStepFail": "stop", 
    "concurrency": 1, 
    "enabled": true, 
    "externalUuid4": "0aa57a27-4008-47fc-96ec-ecb5dad5c114", 
    "isBlueprint": false, 
    "key": "downloadandinstallcygwinpackageonwindows", 
    "links": [
        {
            "stepKey": "downloadcygwininstalleronwindows"
        }, 
        {
            "stepKey": "installcygwinonwindows"
        }, 
        {
            "stepKey": "cleanupcygwininstallationonwindows"
        }
    ], 
    "name": "Download and Install Cygwin Package on Windows", 
    "type": "com.servertribe.attune.tuples.StepGroupTuple"
}